complexnetwork/__init__.py
complexnetwork/avalanche.py
complexnetwork/branching_factor.py
complexnetwork/exponent_relationships.py
complexnetwork/information_transfer.py
complexnetwork/ising.py
complexnetwork/power_law.py
complexnetwork/scaling_functions.py
complexnetwork/utils.py
complexnetwork-0.1.2.data/data/LICENSE
complexnetwork-0.1.2.dist-info/LICENSE
complexnetwork-0.1.2.dist-info/METADATA
complexnetwork-0.1.2.dist-info/WHEEL
complexnetwork-0.1.2.dist-info/top_level.txt
complexnetwork-0.1.2.dist-info/RECORD
