Metadata-Version: 2.1
Name: complexnetwork
Version: 0.1.2
Summary: Complex networks and Self-Organized Criticality
Home-page: https://github.com/Saran-nns/self_organized_criticality
Author: Saranraj Nambusubramaniyan
Author-email: saran_nns@hotmail.com
License: OSI Approved :: MIT License
Keywords: Brain-Inspired Computing,Complex Networks,Criticality,Artificial Neural Networks,Neuro Informatics,Spiking Cortical Networks,Neural Connectomics,Neuroscience,Artificial General Intelligence,Neural Information Processing
Platform: UNKNOWN
Classifier: Development Status :: 3 - Alpha
Classifier: Topic :: Scientific/Engineering :: Artificial Intelligence
Classifier: License :: OSI Approved :: MIT License
Classifier: Programming Language :: Python :: 3
Classifier: Programming Language :: Python :: 3.5
Classifier: Programming Language :: Python :: 3.6
Classifier: Programming Language :: Python :: 3.7
Requires-Dist: numpy
Requires-Dist: scipy
Requires-Dist: seaborn
